django_extended_models/__init__.py
django_extended_models/apps.py
django_extended_models/migrations/0001_initial.py
django_extended_models/migrations/__init__.py
django_extended_models/mixins.py
django_extended_models/models.py
django_extended_models/utils.py
django_extended_models-0.1.0.dist-info/LICENSE
django_extended_models-0.1.0.dist-info/METADATA
django_extended_models-0.1.0.dist-info/WHEEL
django_extended_models-0.1.0.dist-info/RECORD
