Metadata-Version: 2.1
Name: django-extended-models
Version: 0.1.0
Summary: A Mixins and Models with Django utilities.
Home-page: https://github.com/EChachati/django-extended-models
License: MIT
Author: Edkar Chachati
Author-email: chachati28@gmail.com
Requires-Python: >=3.9,<4.0
Classifier: License :: OSI Approved :: MIT License
Classifier: Programming Language :: Python :: 3
Classifier: Programming Language :: Python :: 3.9
Classifier: Programming Language :: Python :: 3.10
Classifier: Programming Language :: Python :: 3.11
Classifier: Programming Language :: Python :: 3.12
Requires-Dist: django (>=3.2,<4.0)
Project-URL: Documentation, https://github.com/EChachati/django-extended-models/blob/master/README.md
Project-URL: Repository, https://github.com/EChachati/django-extended-models
